.VERSION
AUTHORS.rst
CONTRIBUTING.rst
HISTORY.rst
LICENSE
MANIFEST.in
Pipfile
Pipfile.lock
README.rst
USAGE.rst
dev-requirements.txt
requirements.txt
setup.cfg
setup.py
docs/Makefile
docs/authors.rst
docs/conf.py
docs/contributing.rst
docs/history.rst
docs/index.rst
docs/installation.rst
docs/readme.rst
docs/usage.rst
emaillib/.VERSION
emaillib/AUTHORS.rst
emaillib/CONTRIBUTING.rst
emaillib/HISTORY.rst
emaillib/LICENSE
emaillib/Pipfile
emaillib/Pipfile.lock
emaillib/README.rst
emaillib/USAGE.rst
emaillib/__init__.py
emaillib/_version.py
emaillib/dev-requirements.txt
emaillib/emaillib.py
emaillib/emaillibexceptions.py
emaillib/requirements.txt
emaillib.egg-info/PKG-INFO
emaillib.egg-info/SOURCES.txt
emaillib.egg-info/dependency_links.txt
emaillib.egg-info/not-zip-safe
emaillib.egg-info/top_level.txt