Metadata-Version: 2.1
Name: emaillib
Version: 1.0.0
Summary: A simple library to ease the sending of emails with utf8 and attachments. 
Home-page: https://github.com/costastf/emaillib
Author: Costas Tyfoxylos
Author-email: costas.tyf@gmail.com
License: MIT
Keywords: emaillib email
Platform: UNKNOWN
Classifier: Development Status :: 4 - Beta
Classifier: Intended Audience :: Developers
Classifier: License :: OSI Approved :: MIT License
Classifier: Natural Language :: English
Classifier: Programming Language :: Python :: 3.7
License-File: LICENSE
License-File: AUTHORS.rst
